full_sub/full_sub.v
module full_sub (
    input a, input b, input cin, output bor, output diff
);
   assign diff = a ^ b ^ cin;
   assign bor = ((~a) & b) | (b & cin) | (cin & (~a));  
endmodule

full_sub/full_sub_tb.v
`include "full_sub.v"
module full_sub_tb();
reg a, b, cin;
wire bor, diff;
full_sub fs(a, b, cin, bor, diff);
initial begin
    $dumpfile("full_sub.vcd");
    $dumpvars(0, full_sub_tb);
    a=0; b=0; cin=0; #2;
    a=0; b=0; cin=1; #2;
    a=0; b=1; cin=0; #2;
    a=0; b=1; cin=1; #2;
    a=1; b=0; cin=0; #2;
    a=1; b=0; cin=1; #2;
    a=1; b=1; cin=0; #2;
    a=1; b=1; cin=1; #2;
end
endmodule

full_sub/full_sub.vcd
$date
	Sun Jun 11 13:48:05 2023
$end
$version
	Icarus Verilog
$end
$timescale
	1s
$end
$scope module full_sub_tb $end
$var wire 1 ! diff $end
$var wire 1 " bor $end
$var reg 1 # a $end
$var reg 1 $ b $end
$var reg 1 % cin $end
$scope module fs $end
$var wire 1 # a $end
$var wire 1 $ b $end
$var wire 1 " bor $end
$var wire 1 % cin $end
$var wire 1 ! diff $end
$upscope $end
$upscope $end
$enddefinitions $end
$comment Show the parameter values. $end
$dumpall
$end
#0
$dumpvars
0%
0$
0#
0"
0!
$end
#2
1"
1!
1%
#4
0%
1$
#6
0!
1%
#8
0"
1!
0%
0$
1#
#10
0!
1%
#12
0%
1$
#14
1"
1!
1%
