Shift Registers/pipo/pipo.v
module pipo (
    input clk, rst, input [3:0] d, output reg [3:0] q
);
    always @(posedge clk) begin
        if(rst) 
        q <= 4'b0000;
        else
        q <= d;
    end
endmodule

Shift Registers/pipo/pipo_tb.v
`include "pipo.v"
module pipo_tb();
reg clk, rst;
reg [3:0] d;
wire [3:0] q;
pipo pr(clk, rst, d, q);
initial begin
    $dumpfile("pipo.vcd");
    $dumpvars(0, pipo_tb);
end
initial begin
    clk=0;
    forever #5 clk=~clk;
end
initial begin
    rst=1;
    #2 rst=1'b0;
    #2 d=4'b1100;
    #2 d=4'b1101;
    #2 d=4'b0100;
    #2 d=4'b0011;
    #2 d=4'b1111;
    #2 d=4'b1110;
    $finish;
end
endmodule

Shift Registers/pipo/pipo.vcd
$date
	Mon Jun 12 17:40:15 2023
$end
$version
	Icarus Verilog
$end
$timescale
	1s
$end
$scope module pipo_tb $end
$var wire 4 ! q [3:0] $end
$var reg 1 " clk $end
$var reg 4 # d [3:0] $end
$var reg 1 $ rst $end
$scope module pr $end
$var wire 1 " clk $end
$var wire 4 % d [3:0] $end
$var wire 1 $ rst $end
$var reg 4 & q [3:0] $end
$upscope $end
$upscope $end
$enddefinitions $end
$comment Show the parameter values. $end
$dumpall
$end
#0
$dumpvars
bx &
bx %
1$
bx #
0"
bx !
$end
#2
0$
#4
b1100 #
b1100 %
#5
b1100 !
b1100 &
1"
#6
b1101 #
b1101 %
#8
b100 #
b100 %
#10
b11 #
b11 %
0"
#12
b1111 #
b1111 %
#14
b1110 #
b1110 %
