decoder/dec3to8/dec3to8.v
module dec3to8 (
    input [2:0] in, input en, output reg [7:0] y
);
  always@(in or en) begin
    if(en == 0) begin
        y = 8'b00000000;
    end
    else
    begin
        case (in)
            3'b000 : y = 8'b00000001;
            3'b001 : y = 8'b00000010;
            3'b010 : y = 8'b00000100;
            3'b011 : y = 8'b00001000;
            3'b100 : y = 8'b00010000;
            3'b101 : y = 8'b00100000;
            3'b110 : y = 8'b01000000;
            3'b111 : y = 8'b10000000; 
            default: y = 8'bxxxxxxxx;
        endcase
    end 
  end  
endmodule

decoder/dec3to8/dec3to8_tb.v
`include "dec3to8.v"
module dec3to8_tb();
reg [2:0] in;
reg en;
wire [7:0] y;
dec3to8 dc(in, en, y);
initial begin
    $dumpfile("dec3to8.vcd");
    $dumpvars(0, dec3to8_tb);
    en = 0;
    #2 en=1;
    #1 in=3'b000;
    #1 in=3'b001;
    #1 in=3'b010;
    #1 in=3'b011;
    #1 in=3'b100;
    #1 in=3'b101;
    #1 in=3'b110;
    #1 in=3'b111;
end
endmodule

decoder/dec3to8/dec3to8.vcd
$date
	Sun Jun 11 13:43:51 2023
$end
$version
	Icarus Verilog
$end
$timescale
	1s
$end
$scope module dec3to8_tb $end
$var wire 8 ! y [7:0] $end
$var reg 1 " en $end
$var reg 3 # in [2:0] $end
$scope module dc $end
$var wire 1 " en $end
$var wire 3 $ in [2:0] $end
$var reg 8 % y [7:0] $end
$upscope $end
$upscope $end
$enddefinitions $end
$comment Show the parameter values. $end
$dumpall
$end
#0
$dumpvars
b0 %
bx $
bx #
0"
b0 !
$end
#2
bx !
bx %
1"
#3
b1 !
b1 %
b0 #
b0 $
#4
b10 !
b10 %
b1 #
b1 $
#5
b100 !
b100 %
b10 #
b10 $
#6
b1000 !
b1000 %
b11 #
b11 $
#7
b10000 !
b10000 %
b100 #
b100 $
#8
b100000 !
b100000 %
b101 #
b101 $
#9
b1000000 !
b1000000 %
b110 #
b110 $
#10
b10000000 !
b10000000 %
b111 #
b111 $
