BCD to Excess-3/bcd_to_excess3.v
module bcd_to_excess3 (
    input [3:0] b, output [3:0] e
);
    assign e[0] = ~b[0];
    assign e[1] = (b[1] & b[0]) | ((~b[1]) & (~b[0]));
    assign e[2] = ((~b[2]) & b[1]) | ((~b[2]) & b[0]) | (b[2] & (~b[1]) & (~b[0]));
    assign e[3] = b[3] | (b[2] & b[1]) | (b[2] & b[0]);
    endmodule

BCD to Excess-3/bcd_to_excess3_tb.v
`include "bcd_to_excess3.v"
module bcd_to_excess3_tb();
reg [3:0] b;
wire [3:0] e;
bcd_to_excess3 be(b, e);
initial begin
    $dumpfile("bcd_to_excess3.vcd");
    $dumpvars(0, bcd_to_excess3_tb);
    #1 b=4'b0000;
    #1 b=4'b0001;
    #1 b=4'b0010;
    #1 b=4'b0011;
    #1 b=4'b0100;
    #1 b=4'b0101;
    #1 b=4'b0111;
    #1 b=4'b1000;
    #1 b=4'b1001;
    #1 b=3'b000;
end
endmodule

BCD to Excess-3/bcd_to_excess3.vcd
$date
	Tue Jun 13 16:29:10 2023
$end
$version
	Icarus Verilog
$end
$timescale
	1s
$end
$scope module bcd_to_excess3_tb $end
$var wire 4 ! e [3:0] $end
$var reg 4 " b [3:0] $end
$scope module be $end
$var wire 4 # b [3:0] $end
$var wire 4 $ e [3:0] $end
$upscope $end
$upscope $end
$enddefinitions $end
$comment Show the parameter values. $end
$dumpall
$end
#0
$dumpvars
bx $
bx #
bx "
bx !
$end
#1
b11 !
b11 $
b0 "
b0 #
#2
b100 !
b100 $
b1 "
b1 #
#3
b101 !
b101 $
b10 "
b10 #
#4
b110 !
b110 $
b11 "
b11 #
#5
b111 !
b111 $
b100 "
b100 #
#6
b1000 !
b1000 $
b101 "
b101 #
#7
b1010 !
b1010 $
b111 "
b111 #
#8
b1011 !
b1011 $
b1000 "
b1000 #
#9
b1100 !
b1100 $
b1001 "
b1001 #
#10
b11 !
b11 $
b0 "
b0 #
