Counters/Ring Counter/ring_counter.v
module ring_counter (
    input clk, rst, output reg [3:0] q
);
    always @(posedge clk) begin
        if(rst)
        q <= 4'b1000;
        else begin
            q[0] <= q[1];
            q[1] <= q[2];
            q[2] <= q[3];
            q[3] <= q[0];
        end
    end
endmodule

Counters/Ring Counter/ring_counter_tb.v
`include "ring_counter.v"
module ring_counter_tb();
reg clk, rst;
wire [3:0] q;
ring_counter rc(clk, rst, q);
initial begin
    clk=0;
    forever #5 clk=~clk;
end
initial begin
    rst=1;
    #10 rst=0;
    #30 rst=1;
    #20 rst=0;
    $finish;
end
initial begin
    $dumpfile("ring_counter.vcd");
    $dumpvars(0, ring_counter_tb);
end
endmodule

Counters/Ring Counter/ring_counter.vcd
$date
	Mon Jun 12 16:17:35 2023
$end
$version
	Icarus Verilog
$end
$timescale
	1s
$end
$scope module ring_counter_tb $end
$var wire 4 ! q [3:0] $end
$var reg 1 " clk $end
$var reg 1 # rst $end
$scope module rc $end
$var wire 1 " clk $end
$var wire 1 # rst $end
$var reg 4 $ q [3:0] $end
$upscope $end
$upscope $end
$enddefinitions $end
$comment Show the parameter values. $end
$dumpall
$end
#0
$dumpvars
bx $
1#
0"
bx !
$end
#5
b1000 !
b1000 $
1"
#10
0"
0#
#15
b100 !
b100 $
1"
#20
0"
#25
b10 !
b10 $
1"
#30
0"
#35
b1 !
b1 $
1"
#40
0"
1#
#45
b1000 !
b1000 $
1"
#50
0"
#55
1"
#60
0"
0#
