flipflops/sr ff without rst/srff.v
module srff (
    input s, r, clk, output reg q, qbar
);
    always@(posedge clk) begin
        case ({s, r})
            2'b00 : {q, qbar} <= {q, qbar};
            2'b01 : {q, qbar} <= {1'b0, 1'b1};
            2'b10 : {q, qbar} <= {1'b1, 1'b0};
            2'b11 : {q, qbar} <= {1'bx, 1'bx}; 
            default: begin
                
            end
        endcase
        
    end
endmodule

flipflops/sr ff without rst/srff_tb.v
`include "srff.v"
module srff_tb();
reg clk, s, r;
wire q, qbar;
srff sr1(s, r, clk, q, qbar);
initial begin
    clk=0; 
    forever #5 clk=~clk;
end
initial begin
    #10; s=1'b0; r=1'b0;
    #10; s=1'b0; r=1'b1;
    #10; s=1'b1; r=1'b0;
    #10; s=1'b1; r=1'b1;
    #10; $finish;
end
initial begin
    $dumpfile("srff.vcd");
    $dumpvars(0, srff_tb);
end

endmodule

flipflops/sr ff without rst/srff.vcd
$date
	Mon Jun 12 09:12:56 2023
$end
$version
	Icarus Verilog
$end
$timescale
	1s
$end
$scope module srff_tb $end
$var wire 1 ! qbar $end
$var wire 1 " q $end
$var reg 1 # clk $end
$var reg 1 $ r $end
$var reg 1 % s $end
$scope module sr1 $end
$var wire 1 # clk $end
$var wire 1 $ r $end
$var wire 1 % s $end
$var reg 1 " q $end
$var reg 1 ! qbar $end
$upscope $end
$upscope $end
$enddefinitions $end
$comment Show the parameter values. $end
$dumpall
$end
#0
$dumpvars
x%
x$
0#
x"
x!
$end
#5
1#
#10
0#
0$
0%
#15
1#
#20
0#
1$
#25
0"
1!
1#
#30
0#
0$
1%
#35
1"
0!
1#
#40
0#
1$
#45
x"
x!
1#
