flipflops/jk ff/jkff.v
module jkff (
    input j, k, clk, rst, output reg q, qbar
);
    always@(posedge clk) begin
        if({rst})
        {q, qbar} <= {1'b0, 1'b1};
        else begin
            case ({j, k})
                2'b00 : {q, qbar} <= {q, qbar};
                2'b01 : {q, qbar} <= {1'b0, 1'b1};
                2'b10 : {q, qbar} <= {1'b1, 1'b0};
                2'b11 : {q, qbar} <= {~q, q}; 
                default: begin
                    
                end
            endcase
        end
    end
endmodule

flipflops/jk ff/jkff_tb.v
`include "jkff.v"
module jkff_tb();
reg clk, rst, j, k;
wire q, qbar;
jkff jf(j, k, clk, rst, q, qbar);
initial begin
    clk=0;
    forever #5 clk=~clk;
end
initial begin
    rst=1; #10;
    rst=0; j=1'b0; k=1'b0; #10;
    j=1'b0; k=1'b1; #10;
    j=1'b1; k=1'b0; #10;
    j=1'b1; k=1'b1; #10;
    $finish;
end
initial begin
    $dumpfile("jkff.vcd");
    $dumpvars(0, jkff_tb);
end
endmodule

flipflops/jk ff/jkff.vcd
$date
	Mon Jun 12 08:34:46 2023
$end
$version
	Icarus Verilog
$end
$timescale
	1s
$end
$scope module jkff_tb $end
$var wire 1 ! qbar $end
$var wire 1 " q $end
$var reg 1 # clk $end
$var reg 1 $ j $end
$var reg 1 % k $end
$var reg 1 & rst $end
$scope module jf $end
$var wire 1 # clk $end
$var wire 1 $ j $end
$var wire 1 % k $end
$var wire 1 & rst $end
$var reg 1 " q $end
$var reg 1 ! qbar $end
$upscope $end
$upscope $end
$enddefinitions $end
$comment Show the parameter values. $end
$dumpall
$end
#0
$dumpvars
1&
x%
x$
0#
x"
x!
$end
#5
0"
1!
1#
#10
0#
0%
0$
0&
#15
1#
#20
0#
1%
#25
1#
#30
0#
0%
1$
#35
1"
0!
1#
#40
0#
1%
#45
0"
1!
1#
