BCD to binary/bcd_to_bin.v
module bcd_to_bin (
    input [7:0] bcd, output [3:0] bin
);
   assign bin[0] = bcd[0];
   assign bin[1] = bcd[1] ^ bcd[4];
   assign bin[2] = bcd[2] | (bcd[4] & bcd[1]);
   assign bin[3] = bcd[3] | bcd[4]; 
endmodule

BCD to binary/bcd_to_binary_tb.v
`include "bcd_to_bin.v"
module bcd_to_bin_tb();
reg [7:0] bcd;
wire [3:0] bin;
bcd_to_bin bd(bcd, bin);
initial begin
    $dumpfile("bcd_to_bin.vcd");
    $dumpvars(0, bcd_to_bin_tb);
    #1 bcd=8'b0;
    #1 bcd=8'b10;
    #1 bcd=8'b100;
    #1 bcd=8'b111;
    #1 bcd=8'b1000;
    #1 bcd=8'b10001;
    #1 bcd=8'b10011;
    #1 bcd=8'b10101;
end
endmodule

BCD to binary/bcd_to_bin.vcd
$date
	Tue Jun 13 16:16:31 2023
$end
$version
	Icarus Verilog
$end
$timescale
	1s
$end
$scope module bcd_to_bin_tb $end
$var wire 4 ! bin [3:0] $end
$var reg 8 " bcd [7:0] $end
$scope module bd $end
$var wire 8 # bcd [7:0] $end
$var wire 4 $ bin [3:0] $end
$upscope $end
$upscope $end
$enddefinitions $end
$comment Show the parameter values. $end
$dumpall
$end
#0
$dumpvars
bx $
bx #
bx "
bx !
$end
#1
b0 !
b0 $
b0 "
b0 #
#2
b10 !
b10 $
b10 "
b10 #
#3
b100 !
b100 $
b100 "
b100 #
#4
b111 !
b111 $
b111 "
b111 #
#5
b1000 !
b1000 $
b1000 "
b1000 #
#6
b1011 !
b1011 $
b10001 "
b10001 #
#7
b1101 !
b1101 $
b10011 "
b10011 #
#8
b1111 !
b1111 $
b10101 "
b10101 #
