BCD to 7-segment display/bcdto7seg.v
module bcdto7seg (
    input [3:0] bcd, output reg [6:0] seg
);
   always @(bcd) begin
    case (bcd)
        0 : seg = 7'b1111110;
        1 : seg = 7'b0110000;
        2 : seg = 7'b1101101;
        3 : seg = 7'b1111001;
        4 : seg = 7'b0110011;
        5 : seg = 7'b1011011;
        6 : seg = 7'b1011111;
        7 : seg = 7'b1110000;
        8 : seg = 7'b1111111;
        9 : seg = 7'b1111011;
        default: seg = 7'b0000000;
    endcase
   end 
endmodule

BCD to 7-segment display/bcdto7seg_tb.v
`include "bcdto7seg.v"
module bcdto7seg_tb();
reg [3:0] bcd;
wire [6:0] seg;
integer i;
bcdto7seg bc(bcd, seg);
initial begin
    $dumpfile("bcdto7seg.vcd");
    $dumpvars(0, bcdto7seg_tb);
    for(i=0; i<10; i++) begin
        #10 bcd=i;
    end
end
endmodule

BCD to 7-segment display/bcdto7seg.vcd
$date
	Tue Jun 13 16:07:43 2023
$end
$version
	Icarus Verilog
$end
$timescale
	1s
$end
$scope module bcdto7seg_tb $end
$var wire 7 ! seg [6:0] $end
$var reg 4 " bcd [3:0] $end
$var integer 32 # i [31:0] $end
$scope module bc $end
$var wire 4 $ bcd [3:0] $end
$var reg 7 % seg [6:0] $end
$upscope $end
$upscope $end
$enddefinitions $end
$comment Show the parameter values. $end
$dumpall
$end
#0
$dumpvars
bx %
bx $
b0 #
bx "
bx !
$end
#10
b1111110 !
b1111110 %
b1 #
b0 "
b0 $
#20
b110000 !
b110000 %
b10 #
b1 "
b1 $
#30
b1101101 !
b1101101 %
b11 #
b10 "
b10 $
#40
b1111001 !
b1111001 %
b100 #
b11 "
b11 $
#50
b110011 !
b110011 %
b101 #
b100 "
b100 $
#60
b1011011 !
b1011011 %
b110 #
b101 "
b101 $
#70
b1011111 !
b1011111 %
b111 #
b110 "
b110 $
#80
b1110000 !
b1110000 %
b1000 #
b111 "
b111 $
#90
b1111111 !
b1111111 %
b1001 #
b1000 "
b1000 $
#100
b1111011 !
b1111011 %
b1010 #
b1001 "
b1001 $
