Binary to BCD/bin_to_bcd.v
module bin_to_bcd (
    input [7:0] bin, output [11:0] bcd
);
    reg [3:0] h, t, o;
    reg [6:0] temp;
    
    always @(*) begin
        h = bin/100;
        temp = bin%100;
        t = temp/10;
        o = temp%10;
    end

    assign bcd = {h, t, o};
endmodule

Binary to BCD/bin_to_bcd_tb.v
`include "bin_to_bcd.v"
module bin_to_bcd_tb();
reg [7:0] bin;
wire [11:0] bcd;
integer i;
bin_to_bcd b1(bin, bcd);
initial begin
    $dumpfile("bin2bcd.vcd");
    $dumpvars(0, bin_to_bcd_tb);
    for(i=0; i<256; i++) begin
        #2 bin=i;
    end
end
endmodule

Binary to BCD/bin2bcd.vcd
$date
	Tue Jun 13 16:37:09 2023
$end
$version
	Icarus Verilog
$end
$timescale
	1s
$end
$scope module bin_to_bcd_tb $end
$var wire 12 ! bcd [11:0] $end
$var reg 8 " bin [7:0] $end
$var integer 32 # i [31:0] $end
$scope module b1 $end
$var wire 8 $ bin [7:0] $end
$var wire 12 % bcd [11:0] $end
$var reg 4 & h [3:0] $end
$var reg 4 ' o [3:0] $end
$var reg 4 ( t [3:0] $end
$var reg 7 ) temp [6:0] $end
$upscope $end
$upscope $end
$enddefinitions $end
$comment Show the parameter values. $end
$dumpall
$end
#0
$dumpvars
bx )
bx (
bx '
bx &
bx %
bx $
b0 #
bx "
bx !
$end
#2
b0 '
b0 (
b0 )
b0 !
b0 %
b0 &
b1 #
b0 "
b0 $
#4
b1 !
b1 %
b1 '
b1 )
b10 #
b1 "
b1 $
#6
b10 !
b10 %
b10 '
b10 )
b11 #
b10 "
b10 $
#8
b11 !
b11 %
b11 '
b11 )
b100 #
b11 "
b11 $
#10
b100 !
b100 %
b100 '
b100 )
b101 #
b100 "
b100 $
#12
b101 !
b101 %
b101 '
b101 )
b110 #
b101 "
b101 $
#14
b110 !
b110 %
b110 '
b110 )
b111 #
b110 "
b110 $
#16
b111 !
b111 %
b111 '
b111 )
b1000 #
b111 "
b111 $
#18
b1000 !
b1000 %
b1000 '
b1000 )
b1001 #
b1000 "
b1000 $
#20
b1001 !
b1001 %
b1001 '
b1001 )
b1010 #
b1001 "
b1001 $
#22
b0 '
b10000 !
b10000 %
b1 (
b1010 )
b1011 #
b1010 "
b1010 $
#24
b10001 !
b10001 %
b1 '
b1011 )
b1100 #
b1011 "
b1011 $
#26
b10010 !
b10010 %
b10 '
b1100 )
b1101 #
b1100 "
b1100 $
#28
b10011 !
b10011 %
b11 '
b1101 )
b1110 #
b1101 "
b1101 $
#30
b10100 !
b10100 %
b100 '
b1110 )
b1111 #
b1110 "
b1110 $
#32
b10101 !
b10101 %
b101 '
b1111 )
b10000 #
b1111 "
b1111 $
#34
b10110 !
b10110 %
b110 '
b10000 )
b10001 #
b10000 "
b10000 $
#36
b10111 !
b10111 %
b111 '
b10001 )
b10010 #
b10001 "
b10001 $
#38
b11000 !
b11000 %
b1000 '
b10010 )
b10011 #
b10010 "
b10010 $
#40
b11001 !
b11001 %
b1001 '
b10011 )
b10100 #
b10011 "
b10011 $
#42
b0 '
b100000 !
b100000 %
b10 (
b10100 )
b10101 #
b10100 "
b10100 $
#44
b100001 !
b100001 %
b1 '
b10101 )
b10110 #
b10101 "
b10101 $
#46
b100010 !
b100010 %
b10 '
b10110 )
b10111 #
b10110 "
b10110 $
#48
b100011 !
b100011 %
b11 '
b10111 )
b11000 #
b10111 "
b10111 $
#50
b100100 !
b100100 %
b100 '
b11000 )
b11001 #
b11000 "
b11000 $
#52
b100101 !
b100101 %
b101 '
b11001 )
b11010 #
b11001 "
b11001 $
#54
b100110 !
b100110 %
b110 '
b11010 )
b11011 #
b11010 "
b11010 $
#56
b100111 !
b100111 %
b111 '
b11011 )
b11100 #
b11011 "
b11011 $
#58
b101000 !
b101000 %
b1000 '
b11100 )
b11101 #
b11100 "
b11100 $
#60
b101001 !
b101001 %
b1001 '
b11101 )
b11110 #
b11101 "
b11101 $
#62
b0 '
b110000 !
b110000 %
b11 (
b11110 )
b11111 #
b11110 "
b11110 $
#64
b110001 !
b110001 %
b1 '
b11111 )
b100000 #
b11111 "
b11111 $
#66
b110010 !
b110010 %
b10 '
b100000 )
b100001 #
b100000 "
b100000 $
#68
b110011 !
b110011 %
b11 '
b100001 )
b100010 #
b100001 "
b100001 $
#70
b110100 !
b110100 %
b100 '
b100010 )
b100011 #
b100010 "
b100010 $
#72
b110101 !
b110101 %
b101 '
b100011 )
b100100 #
b100011 "
b100011 $
#74
b110110 !
b110110 %
b110 '
b100100 )
b100101 #
b100100 "
b100100 $
#76
b110111 !
b110111 %
b111 '
b100101 )
b100110 #
b100101 "
b100101 $
#78
b111000 !
b111000 %
b1000 '
b100110 )
b100111 #
b100110 "
b100110 $
#80
b111001 !
b111001 %
b1001 '
b100111 )
b101000 #
b100111 "
b100111 $
#82
b0 '
b1000000 !
b1000000 %
b100 (
b101000 )
b101001 #
b101000 "
b101000 $
#84
b1000001 !
b1000001 %
b1 '
b101001 )
b101010 #
b101001 "
b101001 $
#86
b1000010 !
b1000010 %
b10 '
b101010 )
b101011 #
b101010 "
b101010 $
#88
b1000011 !
b1000011 %
b11 '
b101011 )
b101100 #
b101011 "
b101011 $
#90
b1000100 !
b1000100 %
b100 '
b101100 )
b101101 #
b101100 "
b101100 $
#92
b1000101 !
b1000101 %
b101 '
b101101 )
b101110 #
b101101 "
b101101 $
#94
b1000110 !
b1000110 %
b110 '
b101110 )
b101111 #
b101110 "
b101110 $
#96
b1000111 !
b1000111 %
b111 '
b101111 )
b110000 #
b101111 "
b101111 $
#98
b1001000 !
b1001000 %
b1000 '
b110000 )
b110001 #
b110000 "
b110000 $
#100
b1001001 !
b1001001 %
b1001 '
b110001 )
b110010 #
b110001 "
b110001 $
#102
b0 '
b1010000 !
b1010000 %
b101 (
b110010 )
b110011 #
b110010 "
b110010 $
#104
b1010001 !
b1010001 %
b1 '
b110011 )
b110100 #
b110011 "
b110011 $
#106
b1010010 !
b1010010 %
b10 '
b110100 )
b110101 #
b110100 "
b110100 $
#108
b1010011 !
b1010011 %
b11 '
b110101 )
b110110 #
b110101 "
b110101 $
#110
b1010100 !
b1010100 %
b100 '
b110110 )
b110111 #
b110110 "
b110110 $
#112
b1010101 !
b1010101 %
b101 '
b110111 )
b111000 #
b110111 "
b110111 $
#114
b1010110 !
b1010110 %
b110 '
b111000 )
b111001 #
b111000 "
b111000 $
#116
b1010111 !
b1010111 %
b111 '
b111001 )
b111010 #
b111001 "
b111001 $
#118
b1011000 !
b1011000 %
b1000 '
b111010 )
b111011 #
b111010 "
b111010 $
#120
b1011001 !
b1011001 %
b1001 '
b111011 )
b111100 #
b111011 "
b111011 $
#122
b0 '
b1100000 !
b1100000 %
b110 (
b111100 )
b111101 #
b111100 "
b111100 $
#124
b1100001 !
b1100001 %
b1 '
b111101 )
b111110 #
b111101 "
b111101 $
#126
b1100010 !
b1100010 %
b10 '
b111110 )
b111111 #
b111110 "
b111110 $
#128
b1100011 !
b1100011 %
b11 '
b111111 )
b1000000 #
b111111 "
b111111 $
#130
b1100100 !
b1100100 %
b100 '
b1000000 )
b1000001 #
b1000000 "
b1000000 $
#132
b1100101 !
b1100101 %
b101 '
b1000001 )
b1000010 #
b1000001 "
b1000001 $
#134
b1100110 !
b1100110 %
b110 '
b1000010 )
b1000011 #
b1000010 "
b1000010 $
#136
b1100111 !
b1100111 %
b111 '
b1000011 )
b1000100 #
b1000011 "
b1000011 $
#138
b1101000 !
b1101000 %
b1000 '
b1000100 )
b1000101 #
b1000100 "
b1000100 $
#140
b1101001 !
b1101001 %
b1001 '
b1000101 )
b1000110 #
b1000101 "
b1000101 $
#142
b0 '
b1110000 !
b1110000 %
b111 (
b1000110 )
b1000111 #
b1000110 "
b1000110 $
#144
b1110001 !
b1110001 %
b1 '
b1000111 )
b1001000 #
b1000111 "
b1000111 $
#146
b1110010 !
b1110010 %
b10 '
b1001000 )
b1001001 #
b1001000 "
b1001000 $
#148
b1110011 !
b1110011 %
b11 '
b1001001 )
b1001010 #
b1001001 "
b1001001 $
#150
b1110100 !
b1110100 %
b100 '
b1001010 )
b1001011 #
b1001010 "
b1001010 $
#152
b1110101 !
b1110101 %
b101 '
b1001011 )
b1001100 #
b1001011 "
b1001011 $
#154
b1110110 !
b1110110 %
b110 '
b1001100 )
b1001101 #
b1001100 "
b1001100 $
#156
b1110111 !
b1110111 %
b111 '
b1001101 )
b1001110 #
b1001101 "
b1001101 $
#158
b1111000 !
b1111000 %
b1000 '
b1001110 )
b1001111 #
b1001110 "
b1001110 $
#160
b1111001 !
b1111001 %
b1001 '
b1001111 )
b1010000 #
b1001111 "
b1001111 $
#162
b0 '
b10000000 !
b10000000 %
b1000 (
b1010000 )
b1010001 #
b1010000 "
b1010000 $
#164
b10000001 !
b10000001 %
b1 '
b1010001 )
b1010010 #
b1010001 "
b1010001 $
#166
b10000010 !
b10000010 %
b10 '
b1010010 )
b1010011 #
b1010010 "
b1010010 $
#168
b10000011 !
b10000011 %
b11 '
b1010011 )
b1010100 #
b1010011 "
b1010011 $
#170
b10000100 !
b10000100 %
b100 '
b1010100 )
b1010101 #
b1010100 "
b1010100 $
#172
b10000101 !
b10000101 %
b101 '
b1010101 )
b1010110 #
b1010101 "
b1010101 $
#174
b10000110 !
b10000110 %
b110 '
b1010110 )
b1010111 #
b1010110 "
b1010110 $
#176
b10000111 !
b10000111 %
b111 '
b1010111 )
b1011000 #
b1010111 "
b1010111 $
#178
b10001000 !
b10001000 %
b1000 '
b1011000 )
b1011001 #
b1011000 "
b1011000 $
#180
b10001001 !
b10001001 %
b1001 '
b1011001 )
b1011010 #
b1011001 "
b1011001 $
#182
b0 '
b10010000 !
b10010000 %
b1001 (
b1011010 )
b1011011 #
b1011010 "
b1011010 $
#184
b10010001 !
b10010001 %
b1 '
b1011011 )
b1011100 #
b1011011 "
b1011011 $
#186
b10010010 !
b10010010 %
b10 '
b1011100 )
b1011101 #
b1011100 "
b1011100 $
#188
b10010011 !
b10010011 %
b11 '
b1011101 )
b1011110 #
b1011101 "
b1011101 $
#190
b10010100 !
b10010100 %
b100 '
b1011110 )
b1011111 #
b1011110 "
b1011110 $
#192
b10010101 !
b10010101 %
b101 '
b1011111 )
b1100000 #
b1011111 "
b1011111 $
#194
b10010110 !
b10010110 %
b110 '
b1100000 )
b1100001 #
b1100000 "
b1100000 $
#196
b10010111 !
b10010111 %
b111 '
b1100001 )
b1100010 #
b1100001 "
b1100001 $
#198
b10011000 !
b10011000 %
b1000 '
b1100010 )
b1100011 #
b1100010 "
b1100010 $
#200
b10011001 !
b10011001 %
b1001 '
b1100011 )
b1100100 #
b1100011 "
b1100011 $
#202
b0 '
b0 (
b0 )
b100000000 !
b100000000 %
b1 &
b1100101 #
b1100100 "
b1100100 $
#204
b100000001 !
b100000001 %
b1 '
b1 )
b1100110 #
b1100101 "
b1100101 $
#206
b100000010 !
b100000010 %
b10 '
b10 )
b1100111 #
b1100110 "
b1100110 $
#208
b100000011 !
b100000011 %
b11 '
b11 )
b1101000 #
b1100111 "
b1100111 $
#210
b100000100 !
b100000100 %
b100 '
b100 )
b1101001 #
b1101000 "
b1101000 $
#212
b100000101 !
b100000101 %
b101 '
b101 )
b1101010 #
b1101001 "
b1101001 $
#214
b100000110 !
b100000110 %
b110 '
b110 )
b1101011 #
b1101010 "
b1101010 $
#216
b100000111 !
b100000111 %
b111 '
b111 )
b1101100 #
b1101011 "
b1101011 $
#218
b100001000 !
b100001000 %
b1000 '
b1000 )
b1101101 #
b1101100 "
b1101100 $
#220
b100001001 !
b100001001 %
b1001 '
b1001 )
b1101110 #
b1101101 "
b1101101 $
#222
b0 '
b100010000 !
b100010000 %
b1 (
b1010 )
b1101111 #
b1101110 "
b1101110 $
#224
b100010001 !
b100010001 %
b1 '
b1011 )
b1110000 #
b1101111 "
b1101111 $
#226
b100010010 !
b100010010 %
b10 '
b1100 )
b1110001 #
b1110000 "
b1110000 $
#228
b100010011 !
b100010011 %
b11 '
b1101 )
b1110010 #
b1110001 "
b1110001 $
#230
b100010100 !
b100010100 %
b100 '
b1110 )
b1110011 #
b1110010 "
b1110010 $
#232
b100010101 !
b100010101 %
b101 '
b1111 )
b1110100 #
b1110011 "
b1110011 $
#234
b100010110 !
b100010110 %
b110 '
b10000 )
b1110101 #
b1110100 "
b1110100 $
#236
b100010111 !
b100010111 %
b111 '
b10001 )
b1110110 #
b1110101 "
b1110101 $
#238
b100011000 !
b100011000 %
b1000 '
b10010 )
b1110111 #
b1110110 "
b1110110 $
#240
b100011001 !
b100011001 %
b1001 '
b10011 )
b1111000 #
b1110111 "
b1110111 $
#242
b0 '
b100100000 !
b100100000 %
b10 (
b10100 )
b1111001 #
b1111000 "
b1111000 $
#244
b100100001 !
b100100001 %
b1 '
b10101 )
b1111010 #
b1111001 "
b1111001 $
#246
b100100010 !
b100100010 %
b10 '
b10110 )
b1111011 #
b1111010 "
b1111010 $
#248
b100100011 !
b100100011 %
b11 '
b10111 )
b1111100 #
b1111011 "
b1111011 $
#250
b100100100 !
b100100100 %
b100 '
b11000 )
b1111101 #
b1111100 "
b1111100 $
#252
b100100101 !
b100100101 %
b101 '
b11001 )
b1111110 #
b1111101 "
b1111101 $
#254
b100100110 !
b100100110 %
b110 '
b11010 )
b1111111 #
b1111110 "
b1111110 $
#256
b100100111 !
b100100111 %
b111 '
b11011 )
b10000000 #
b1111111 "
b1111111 $
#258
b100101000 !
b100101000 %
b1000 '
b11100 )
b10000001 #
b10000000 "
b10000000 $
#260
b100101001 !
b100101001 %
b1001 '
b11101 )
b10000010 #
b10000001 "
b10000001 $
#262
b0 '
b100110000 !
b100110000 %
b11 (
b11110 )
b10000011 #
b10000010 "
b10000010 $
#264
b100110001 !
b100110001 %
b1 '
b11111 )
b10000100 #
b10000011 "
b10000011 $
#266
b100110010 !
b100110010 %
b10 '
b100000 )
b10000101 #
b10000100 "
b10000100 $
#268
b100110011 !
b100110011 %
b11 '
b100001 )
b10000110 #
b10000101 "
b10000101 $
#270
b100110100 !
b100110100 %
b100 '
b100010 )
b10000111 #
b10000110 "
b10000110 $
#272
b100110101 !
b100110101 %
b101 '
b100011 )
b10001000 #
b10000111 "
b10000111 $
#274
b100110110 !
b100110110 %
b110 '
b100100 )
b10001001 #
b10001000 "
b10001000 $
#276
b100110111 !
b100110111 %
b111 '
b100101 )
b10001010 #
b10001001 "
b10001001 $
#278
b100111000 !
b100111000 %
b1000 '
b100110 )
b10001011 #
b10001010 "
b10001010 $
#280
b100111001 !
b100111001 %
b1001 '
b100111 )
b10001100 #
b10001011 "
b10001011 $
#282
b0 '
b101000000 !
b101000000 %
b100 (
b101000 )
b10001101 #
b10001100 "
b10001100 $
#284
b101000001 !
b101000001 %
b1 '
b101001 )
b10001110 #
b10001101 "
b10001101 $
#286
b101000010 !
b101000010 %
b10 '
b101010 )
b10001111 #
b10001110 "
b10001110 $
#288
b101000011 !
b101000011 %
b11 '
b101011 )
b10010000 #
b10001111 "
b10001111 $
#290
b101000100 !
b101000100 %
b100 '
b101100 )
b10010001 #
b10010000 "
b10010000 $
#292
b101000101 !
b101000101 %
b101 '
b101101 )
b10010010 #
b10010001 "
b10010001 $
#294
b101000110 !
b101000110 %
b110 '
b101110 )
b10010011 #
b10010010 "
b10010010 $
#296
b101000111 !
b101000111 %
b111 '
b101111 )
b10010100 #
b10010011 "
b10010011 $
#298
b101001000 !
b101001000 %
b1000 '
b110000 )
b10010101 #
b10010100 "
b10010100 $
#300
b101001001 !
b101001001 %
b1001 '
b110001 )
b10010110 #
b10010101 "
b10010101 $
#302
b0 '
b101010000 !
b101010000 %
b101 (
b110010 )
b10010111 #
b10010110 "
b10010110 $
#304
b101010001 !
b101010001 %
b1 '
b110011 )
b10011000 #
b10010111 "
b10010111 $
#306
b101010010 !
b101010010 %
b10 '
b110100 )
b10011001 #
b10011000 "
b10011000 $
#308
b101010011 !
b101010011 %
b11 '
b110101 )
b10011010 #
b10011001 "
b10011001 $
#310
b101010100 !
b101010100 %
b100 '
b110110 )
b10011011 #
b10011010 "
b10011010 $
#312
b101010101 !
b101010101 %
b101 '
b110111 )
b10011100 #
b10011011 "
b10011011 $
#314
b101010110 !
b101010110 %
b110 '
b111000 )
b10011101 #
b10011100 "
b10011100 $
#316
b101010111 !
b101010111 %
b111 '
b111001 )
b10011110 #
b10011101 "
b10011101 $
#318
b101011000 !
b101011000 %
b1000 '
b111010 )
b10011111 #
b10011110 "
b10011110 $
#320
b101011001 !
b101011001 %
b1001 '
b111011 )
b10100000 #
b10011111 "
b10011111 $
#322
b0 '
b101100000 !
b101100000 %
b110 (
b111100 )
b10100001 #
b10100000 "
b10100000 $
#324
b101100001 !
b101100001 %
b1 '
b111101 )
b10100010 #
b10100001 "
b10100001 $
#326
b101100010 !
b101100010 %
b10 '
b111110 )
b10100011 #
b10100010 "
b10100010 $
#328
b101100011 !
b101100011 %
b11 '
b111111 )
b10100100 #
b10100011 "
b10100011 $
#330
b101100100 !
b101100100 %
b100 '
b1000000 )
b10100101 #
b10100100 "
b10100100 $
#332
b101100101 !
b101100101 %
b101 '
b1000001 )
b10100110 #
b10100101 "
b10100101 $
#334
b101100110 !
b101100110 %
b110 '
b1000010 )
b10100111 #
b10100110 "
b10100110 $
#336
b101100111 !
b101100111 %
b111 '
b1000011 )
b10101000 #
b10100111 "
b10100111 $
#338
b101101000 !
b101101000 %
b1000 '
b1000100 )
b10101001 #
b10101000 "
b10101000 $
#340
b101101001 !
b101101001 %
b1001 '
b1000101 )
b10101010 #
b10101001 "
b10101001 $
#342
b0 '
b101110000 !
b101110000 %
b111 (
b1000110 )
b10101011 #
b10101010 "
b10101010 $
#344
b101110001 !
b101110001 %
b1 '
b1000111 )
b10101100 #
b10101011 "
b10101011 $
#346
b101110010 !
b101110010 %
b10 '
b1001000 )
b10101101 #
b10101100 "
b10101100 $
#348
b101110011 !
b101110011 %
b11 '
b1001001 )
b10101110 #
b10101101 "
b10101101 $
#350
b101110100 !
b101110100 %
b100 '
b1001010 )
b10101111 #
b10101110 "
b10101110 $
#352
b101110101 !
b101110101 %
b101 '
b1001011 )
b10110000 #
b10101111 "
b10101111 $
#354
b101110110 !
b101110110 %
b110 '
b1001100 )
b10110001 #
b10110000 "
b10110000 $
#356
b101110111 !
b101110111 %
b111 '
b1001101 )
b10110010 #
b10110001 "
b10110001 $
#358
b101111000 !
b101111000 %
b1000 '
b1001110 )
b10110011 #
b10110010 "
b10110010 $
#360
b101111001 !
b101111001 %
b1001 '
b1001111 )
b10110100 #
b10110011 "
b10110011 $
#362
b0 '
b110000000 !
b110000000 %
b1000 (
b1010000 )
b10110101 #
b10110100 "
b10110100 $
#364
b110000001 !
b110000001 %
b1 '
b1010001 )
b10110110 #
b10110101 "
b10110101 $
#366
b110000010 !
b110000010 %
b10 '
b1010010 )
b10110111 #
b10110110 "
b10110110 $
#368
b110000011 !
b110000011 %
b11 '
b1010011 )
b10111000 #
b10110111 "
b10110111 $
#370
b110000100 !
b110000100 %
b100 '
b1010100 )
b10111001 #
b10111000 "
b10111000 $
#372
b110000101 !
b110000101 %
b101 '
b1010101 )
b10111010 #
b10111001 "
b10111001 $
#374
b110000110 !
b110000110 %
b110 '
b1010110 )
b10111011 #
b10111010 "
b10111010 $
#376
b110000111 !
b110000111 %
b111 '
b1010111 )
b10111100 #
b10111011 "
b10111011 $
#378
b110001000 !
b110001000 %
b1000 '
b1011000 )
b10111101 #
b10111100 "
b10111100 $
#380
b110001001 !
b110001001 %
b1001 '
b1011001 )
b10111110 #
b10111101 "
b10111101 $
#382
b0 '
b110010000 !
b110010000 %
b1001 (
b1011010 )
b10111111 #
b10111110 "
b10111110 $
#384
b110010001 !
b110010001 %
b1 '
b1011011 )
b11000000 #
b10111111 "
b10111111 $
#386
b110010010 !
b110010010 %
b10 '
b1011100 )
b11000001 #
b11000000 "
b11000000 $
#388
b110010011 !
b110010011 %
b11 '
b1011101 )
b11000010 #
b11000001 "
b11000001 $
#390
b110010100 !
b110010100 %
b100 '
b1011110 )
b11000011 #
b11000010 "
b11000010 $
#392
b110010101 !
b110010101 %
b101 '
b1011111 )
b11000100 #
b11000011 "
b11000011 $
#394
b110010110 !
b110010110 %
b110 '
b1100000 )
b11000101 #
b11000100 "
b11000100 $
#396
b110010111 !
b110010111 %
b111 '
b1100001 )
b11000110 #
b11000101 "
b11000101 $
#398
b110011000 !
b110011000 %
b1000 '
b1100010 )
b11000111 #
b11000110 "
b11000110 $
#400
b110011001 !
b110011001 %
b1001 '
b1100011 )
b11001000 #
b11000111 "
b11000111 $
#402
b0 '
b0 (
b0 )
b1000000000 !
b1000000000 %
b10 &
b11001001 #
b11001000 "
b11001000 $
#404
b1000000001 !
b1000000001 %
b1 '
b1 )
b11001010 #
b11001001 "
b11001001 $
#406
b1000000010 !
b1000000010 %
b10 '
b10 )
b11001011 #
b11001010 "
b11001010 $
#408
b1000000011 !
b1000000011 %
b11 '
b11 )
b11001100 #
b11001011 "
b11001011 $
#410
b1000000100 !
b1000000100 %
b100 '
b100 )
b11001101 #
b11001100 "
b11001100 $
#412
b1000000101 !
b1000000101 %
b101 '
b101 )
b11001110 #
b11001101 "
b11001101 $
#414
b1000000110 !
b1000000110 %
b110 '
b110 )
b11001111 #
b11001110 "
b11001110 $
#416
b1000000111 !
b1000000111 %
b111 '
b111 )
b11010000 #
b11001111 "
b11001111 $
#418
b1000001000 !
b1000001000 %
b1000 '
b1000 )
b11010001 #
b11010000 "
b11010000 $
#420
b1000001001 !
b1000001001 %
b1001 '
b1001 )
b11010010 #
b11010001 "
b11010001 $
#422
b0 '
b1000010000 !
b1000010000 %
b1 (
b1010 )
b11010011 #
b11010010 "
b11010010 $
#424
b1000010001 !
b1000010001 %
b1 '
b1011 )
b11010100 #
b11010011 "
b11010011 $
#426
b1000010010 !
b1000010010 %
b10 '
b1100 )
b11010101 #
b11010100 "
b11010100 $
#428
b1000010011 !
b1000010011 %
b11 '
b1101 )
b11010110 #
b11010101 "
b11010101 $
#430
b1000010100 !
b1000010100 %
b100 '
b1110 )
b11010111 #
b11010110 "
b11010110 $
#432
b1000010101 !
b1000010101 %
b101 '
b1111 )
b11011000 #
b11010111 "
b11010111 $
#434
b1000010110 !
b1000010110 %
b110 '
b10000 )
b11011001 #
b11011000 "
b11011000 $
#436
b1000010111 !
b1000010111 %
b111 '
b10001 )
b11011010 #
b11011001 "
b11011001 $
#438
b1000011000 !
b1000011000 %
b1000 '
b10010 )
b11011011 #
b11011010 "
b11011010 $
#440
b1000011001 !
b1000011001 %
b1001 '
b10011 )
b11011100 #
b11011011 "
b11011011 $
#442
b0 '
b1000100000 !
b1000100000 %
b10 (
b10100 )
b11011101 #
b11011100 "
b11011100 $
#444
b1000100001 !
b1000100001 %
b1 '
b10101 )
b11011110 #
b11011101 "
b11011101 $
#446
b1000100010 !
b1000100010 %
b10 '
b10110 )
b11011111 #
b11011110 "
b11011110 $
#448
b1000100011 !
b1000100011 %
b11 '
b10111 )
b11100000 #
b11011111 "
b11011111 $
#450
b1000100100 !
b1000100100 %
b100 '
b11000 )
b11100001 #
b11100000 "
b11100000 $
#452
b1000100101 !
b1000100101 %
b101 '
b11001 )
b11100010 #
b11100001 "
b11100001 $
#454
b1000100110 !
b1000100110 %
b110 '
b11010 )
b11100011 #
b11100010 "
b11100010 $
#456
b1000100111 !
b1000100111 %
b111 '
b11011 )
b11100100 #
b11100011 "
b11100011 $
#458
b1000101000 !
b1000101000 %
b1000 '
b11100 )
b11100101 #
b11100100 "
b11100100 $
#460
b1000101001 !
b1000101001 %
b1001 '
b11101 )
b11100110 #
b11100101 "
b11100101 $
#462
b0 '
b1000110000 !
b1000110000 %
b11 (
b11110 )
b11100111 #
b11100110 "
b11100110 $
#464
b1000110001 !
b1000110001 %
b1 '
b11111 )
b11101000 #
b11100111 "
b11100111 $
#466
b1000110010 !
b1000110010 %
b10 '
b100000 )
b11101001 #
b11101000 "
b11101000 $
#468
b1000110011 !
b1000110011 %
b11 '
b100001 )
b11101010 #
b11101001 "
b11101001 $
#470
b1000110100 !
b1000110100 %
b100 '
b100010 )
b11101011 #
b11101010 "
b11101010 $
#472
b1000110101 !
b1000110101 %
b101 '
b100011 )
b11101100 #
b11101011 "
b11101011 $
#474
b1000110110 !
b1000110110 %
b110 '
b100100 )
b11101101 #
b11101100 "
b11101100 $
#476
b1000110111 !
b1000110111 %
b111 '
b100101 )
b11101110 #
b11101101 "
b11101101 $
#478
b1000111000 !
b1000111000 %
b1000 '
b100110 )
b11101111 #
b11101110 "
b11101110 $
#480
b1000111001 !
b1000111001 %
b1001 '
b100111 )
b11110000 #
b11101111 "
b11101111 $
#482
b0 '
b1001000000 !
b1001000000 %
b100 (
b101000 )
b11110001 #
b11110000 "
b11110000 $
#484
b1001000001 !
b1001000001 %
b1 '
b101001 )
b11110010 #
b11110001 "
b11110001 $
#486
b1001000010 !
b1001000010 %
b10 '
b101010 )
b11110011 #
b11110010 "
b11110010 $
#488
b1001000011 !
b1001000011 %
b11 '
b101011 )
b11110100 #
b11110011 "
b11110011 $
#490
b1001000100 !
b1001000100 %
b100 '
b101100 )
b11110101 #
b11110100 "
b11110100 $
#492
b1001000101 !
b1001000101 %
b101 '
b101101 )
b11110110 #
b11110101 "
b11110101 $
#494
b1001000110 !
b1001000110 %
b110 '
b101110 )
b11110111 #
b11110110 "
b11110110 $
#496
b1001000111 !
b1001000111 %
b111 '
b101111 )
b11111000 #
b11110111 "
b11110111 $
#498
b1001001000 !
b1001001000 %
b1000 '
b110000 )
b11111001 #
b11111000 "
b11111000 $
#500
b1001001001 !
b1001001001 %
b1001 '
b110001 )
b11111010 #
b11111001 "
b11111001 $
#502
b0 '
b1001010000 !
b1001010000 %
b101 (
b110010 )
b11111011 #
b11111010 "
b11111010 $
#504
b1001010001 !
b1001010001 %
b1 '
b110011 )
b11111100 #
b11111011 "
b11111011 $
#506
b1001010010 !
b1001010010 %
b10 '
b110100 )
b11111101 #
b11111100 "
b11111100 $
#508
b1001010011 !
b1001010011 %
b11 '
b110101 )
b11111110 #
b11111101 "
b11111101 $
#510
b1001010100 !
b1001010100 %
b100 '
b110110 )
b11111111 #
b11111110 "
b11111110 $
#512
b1001010101 !
b1001010101 %
b101 '
b110111 )
b100000000 #
b11111111 "
b11111111 $
