flipflops/sr ff with sync rst/srff.v
module srff (
    input s, r, clk, rst, output reg q, qbar
);
    always@(posedge clk) begin
        if(rst)
        {q, qbar} <= {1'b0, 1'b1};
        else begin
            case ({s, r})
              2'b00 : {q, qbar} <= {q, qbar};
                2'b01 : {q, qbar} <= {1'b0, 1'b1};
                2'b10 : {q, qbar} <= {1'b1, 1'b0};
                2'b11 : {q, qbar} <= {1'bx, 1'bx}; 
                default: begin
                    
                end
            endcase
        end
    end
endmodule

flipflops/sr ff with sync rst/srff_tb.v
`include "srff.v"
module srff_tb();
reg clk, rst, s, r;
wire q, qbar;
srff sr1(s, r, clk, rst, q, qbar);
initial begin
    clk=0; 
    forever #5 clk=~clk;
end
initial begin
    rst=1;
    #10; rst=0;
    #10; s=1'b0; r=1'b0;
    #10; s=1'b0; r=1'b1;
    #10; s=1'b1; r=1'b0;
    #10; s=1'b1; r=1'b1;
    #10; $finish;
end
initial begin
    $dumpfile("srff.vcd");
    $dumpvars(0, srff_tb);
end

endmodule

flipflops/sr ff with sync rst/srff.vcd
$date
	Mon Jun 12 08:40:23 2023
$end
$version
	Icarus Verilog
$end
$timescale
	1s
$end
$scope module srff_tb $end
$var wire 1 ! qbar $end
$var wire 1 " q $end
$var reg 1 # clk $end
$var reg 1 $ r $end
$var reg 1 % rst $end
$var reg 1 & s $end
$scope module sr1 $end
$var wire 1 # clk $end
$var wire 1 $ r $end
$var wire 1 % rst $end
$var wire 1 & s $end
$var reg 1 " q $end
$var reg 1 ! qbar $end
$upscope $end
$upscope $end
$enddefinitions $end
$comment Show the parameter values. $end
$dumpall
$end
#0
$dumpvars
x&
1%
x$
0#
x"
x!
$end
#5
0"
1!
1#
#10
0#
0%
#15
1#
#20
0#
0$
0&
#25
1#
#30
0#
1$
#35
1#
#40
0#
0$
1&
#45
1"
0!
1#
#50
0#
1$
#55
x"
x!
1#
