Counters/BCD counter/bcd_counter.v
module bcd_counter (
    input clk, rst, output reg [3:0] q
);
    always @(posedge clk) begin
        if(rst) 
        q <= 4'b0000;
        else if(q <= 4'b1001)
        q <= q+1;
        else if(q == 4'b1001)
        q <= 4'b0000;
    end
endmodule

Counters/BCD counter/bcd_counter_tb.v
`include "bcd_counter.v"
module bcd_counter_tb();
reg clk, rst;
wire [3:0] q;
bcd_counter bc(clk, rst, q);
initial begin
    clk=0;
    forever #5 clk=~clk;
end
initial begin
    rst=1;
    #10 rst=0;
    #10 rst=1;
    #10 rst=0;
    #10 rst=1;
    #10 $finish;
end
initial begin
    $dumpfile("bcd_counter.vcd");
    $dumpvars(0, bcd_counter_tb);
end
endmodule

Counters/BCD counter/bcd_counter.vcd
$date
	Mon Jun 12 15:49:27 2023
$end
$version
	Icarus Verilog
$end
$timescale
	1s
$end
$scope module bcd_counter_tb $end
$var wire 4 ! q [3:0] $end
$var reg 1 " clk $end
$var reg 1 # rst $end
$scope module bc $end
$var wire 1 " clk $end
$var wire 1 # rst $end
$var reg 4 $ q [3:0] $end
$upscope $end
$upscope $end
$enddefinitions $end
$comment Show the parameter values. $end
$dumpall
$end
#0
$dumpvars
bx $
1#
0"
bx !
$end
#5
b0 !
b0 $
1"
#10
0"
0#
#15
b1 !
b1 $
1"
#20
0"
1#
#25
b0 !
b0 $
1"
#30
0"
0#
#35
b1 !
b1 $
1"
#40
0"
1#
#45
b0 !
b0 $
1"
