full_adder/full_adder.v
module full_adder (
    input a, input b, input cin, output s, output cout
);
   assign s = a ^ b ^ cin;
   assign cout = (a & b) | (b & cin) | (cin & a); 
endmodule

full_adder/full_adder_tb.v
`include "full_adder.v"
module full_adder_tb();
reg a, b, cin;
wire s, cout;
full_adder fa(a, b, cin, s, cout);
initial begin
    $dumpfile("full_adder.vcd");
    $dumpvars(0, full_adder_tb);
    a=0; b=0; cin=0; #2;
    a=0; b=0; cin=1; #2;
    a=0; b=1; cin=0; #2;
    a=0; b=1; cin=1; #2;
    a=1; b=0; cin=0; #2;
    a=1; b=0; cin=1; #2;
    a=1; b=1; cin=0; #2;
    a=1; b=1; cin=1; #2;
end
endmodule

full_adder/full_adder.vcd
$date
	Sun Jun 11 13:46:59 2023
$end
$version
	Icarus Verilog
$end
$timescale
	1s
$end
$scope module full_adder_tb $end
$var wire 1 ! s $end
$var wire 1 " cout $end
$var reg 1 # a $end
$var reg 1 $ b $end
$var reg 1 % cin $end
$scope module fa $end
$var wire 1 # a $end
$var wire 1 $ b $end
$var wire 1 % cin $end
$var wire 1 " cout $end
$var wire 1 ! s $end
$upscope $end
$upscope $end
$enddefinitions $end
$comment Show the parameter values. $end
$dumpall
$end
#0
$dumpvars
0%
0$
0#
0"
0!
$end
#2
1!
1%
#4
0%
1$
#6
1"
0!
1%
#8
0"
1!
0%
0$
1#
#10
1"
0!
1%
#12
0%
1$
#14
1!
1%
